{
  "64": {
    "route": "72",
    "last_stop_name": "Selfoss",
    "day_types": [
      {
        "day_types": [
          "6",
          "2",
          "4"
        ],
        "times": [
          "07:35",
          "17:11"
        ]
      },
      {
        "day_types": [
          "5",
          "3"
        ],
        "times": [
          "07:35",
          "17:11",
          "18:56"
        ]
      },
      {
        "day_types": [
          "8",
          "10",
          "9",
          "1"
        ],
        "times": [
          "19:30"
        ]
      },
      {
        "day_types": [
          "7"
        ],
        "times": [
          "17:25"
        ]
      }
    ]
  },
  "65": {
    "route": "73",
    "last_stop_name": "Selfoss",
    "day_types": [
      {
        "day_types": [
          "3",
          "5"
        ],
        "times": [
          "06:45",
          "16:30",
          "18:23"
        ]
      },
      {
        "day_types": [
          "8",
          "10",
          "9",
          "1"
        ],
        "times": [
          "16:53"
        ]
      },
      {
        "day_types": [
          "2",
          "4"
        ],
        "times": [
          "06:45",
          "16:30"
        ]
      },
      {
        "day_types": [
          "7"
        ],
        "times": [
          "18:53"
        ]
      },
      {
        "day_types": [
          "6"
        ],
        "times": [
          "06:45",
          "12:17",
          "16:30"
        ]
      }
    ]
  }
}