{
  "57": {
    "route": "57",
    "last_stop_name": "Akureyri",
    "day_types": [
      {
        "day_types": [
          "1",
          "6",
          "9",
          "2",
          "7",
          "4",
          "5",
          "8",
          "3",
          "10"
        ],
        "times": [
          "13:15",
          "21:45"
        ]
      }
    ]
  },
  "56": {
    "route": "57",
    "last_stop_name": "Reykjavík",
    "day_types": [
      {
        "day_types": [
          "1",
          "6",
          "9",
          "2",
          "7",
          "4",
          "5",
          "8",
          "3",
          "10"
        ],
        "times": [
          "12:31",
          "18:36"
        ]
      }
    ]
  }
}