{
  "39": {
    "route": "22",
    "last_stop_name": "Hraun",
    "day_types": [
      {
        "day_types": [
          "6",
          "9",
          "2",
          "4",
          "5",
          "3"
        ],
        "times": [
          "06:53",
          "07:23",
          "07:53",
          "08:23",
          "08:53",
          "09:23",
          "09:53",
          "10:23",
          "10:53",
          "11:23",
          "11:53",
          "12:23",
          "12:53"
        ]
      }
    ]
  }
}