{
  "33": {
    "route": "23",
    "last_stop_name": "Ásgarður",
    "day_types": [
      {
        "day_types": [
          "8"
        ],
        "times": [
          "08:15",
          "08:45",
          "09:15",
          "09:45",
          "10:15",
          "10:45",
          "11:15",
          "11:45",
          "12:15",
          "12:45",
          "13:34",
          "14:04",
          "14:34"
        ]
      },
      {
        "day_types": [
          "7"
        ],
        "times": [
          "08:15",
          "08:45",
          "09:15",
          "09:45",
          "10:15",
          "10:45",
          "11:15",
          "11:45",
          "12:15",
          "12:45",
          "13:34",
          "14:04",
          "14:34",
          "15:04",
          "15:34",
          "16:04",
          "16:34",
          "17:04",
          "17:34",
          "18:04",
          "18:34",
          "19:04",
          "19:34",
          "20:04",
          "20:34"
        ]
      },
      {
        "day_types": [
          "2",
          "3",
          "4",
          "5",
          "6"
        ],
        "times": [
          "07:15",
          "07:45",
          "08:15",
          "08:45",
          "09:15",
          "10:15",
          "11:15",
          "12:15",
          "13:34"
        ]
      }
    ]
  }
}